idev/__init__.py
idev/idev.py
idev-0.1.dist-info/LICENSE.txt
idev-0.1.dist-info/METADATA
idev-0.1.dist-info/WHEEL
idev-0.1.dist-info/top_level.txt
idev-0.1.dist-info/RECORD
