Metadata-Version: 2.1
Name: idev
Version: 0.1
Summary: Termux framework para la api de termux en pytjon
Home-page: https://github.com/h-whokf/idev
Author: joaquin osorio vazquez
Author-email: kemalmoto.e5@gmail.com
License: GPLv3
Project-URL: Bug Tracker, https://github.com/pypa/sampleproject/issues
Platform: UNKNOWN
Classifier: Programming Language :: Python :: 3
Classifier: License :: OSI Approved :: GNU General Public License v3 (GPLv3)
Classifier: Development Status :: 4 - Beta
Classifier: Intended Audience :: Developers
Classifier: Operating System :: OS Independent
Requires-Python: >=3.6
